byteshare/__init__.py
byteshare/py.typed
byteshare-0.0.1.dist-info/METADATA
byteshare-0.0.1.dist-info/WHEEL
byteshare-0.0.1.dist-info/licenses/LICENSE
byteshare-0.0.1.dist-info/RECORD
