Metadata-Version: 2.4
Name: byteshare
Version: 0.0.1
Summary: A lightweight, distributed tensor store for ML inference. The spiritual successor to Apache Plasma, without the Ray dependency.
Project-URL: Homepage, https://github.com/byteshare/byteshare
Project-URL: Documentation, https://github.com/byteshare/byteshare
Project-URL: Repository, https://github.com/byteshare/byteshare
Project-URL: Issues, https://github.com/byteshare/byteshare/issues
Author: ByteShare Contributors
License: Apache-2.0
License-File: LICENSE
Keywords: distributed,inference,machine-learning,object-store,shared-memory,tensor,zero-copy
Classifier: Development Status :: 2 - Pre-Alpha
Classifier: Intended Audience :: Developers
Classifier: Intended Audience :: Science/Research
Classifier: License :: OSI Approved :: Apache Software License
Classifier: Operating System :: OS Independent
Classifier: Programming Language :: Python :: 3
Classifier: Programming Language :: Python :: 3.10
Classifier: Programming Language :: Python :: 3.11
Classifier: Programming Language :: Python :: 3.12
Classifier: Topic :: Scientific/Engineering :: Artificial Intelligence
Classifier: Topic :: System :: Distributed Computing
Requires-Python: >=3.10
Provides-Extra: all
Requires-Dist: boto3>=1.26; extra == 'all'
Requires-Dist: pyzmq>=25.0; extra == 'all'
Requires-Dist: redis>=4.0; extra == 'all'
Provides-Extra: dev
Requires-Dist: pytest-asyncio>=0.21; extra == 'dev'
Requires-Dist: pytest>=7.0; extra == 'dev'
Requires-Dist: ruff>=0.1; extra == 'dev'
Provides-Extra: redis
Requires-Dist: redis>=4.0; extra == 'redis'
Provides-Extra: s3
Requires-Dist: boto3>=1.26; extra == 's3'
Provides-Extra: zmq
Requires-Dist: pyzmq>=25.0; extra == 'zmq'
